techieray_ai_reg_tracker_api/__init__.py
techieray_ai_reg_tracker_api/main.py
techieray_ai_reg_tracker_api-3.0.2.dist-info/LICENSE
techieray_ai_reg_tracker_api-3.0.2.dist-info/METADATA
techieray_ai_reg_tracker_api-3.0.2.dist-info/WHEEL
techieray_ai_reg_tracker_api-3.0.2.dist-info/top_level.txt
techieray_ai_reg_tracker_api-3.0.2.dist-info/RECORD
