Metadata-Version: 2.1
Name: techieray-ai-reg-tracker-api
Version: 3.0.2
License-File: LICENSE
Requires-Dist: requests
